{
    "topics": [
        {
            "id": "topic_guoshoujing",
            "title": "仰望星空的人：郭守敬与授时历 (Guo Shoujing)",
            "type": "china",
            "year": "1231年-1316年",
            "summary": "郭守敬（1231-1316），字若思，顺德邢台人，元朝最杰出的科学家，在天文学、数学、水利工程、地理测量等领域均取得了世界级的成就。他受忽必烈之命，主持编制了当时世界上最精确的历法——<strong>《授时历》</strong>，其精确度与现代公历相当，但早了300年。他还设计制造了简仪、高表等近20种天文仪器，并主持了贯通南北大运河（通惠河）的开凿工程。他不仅是一位理论家，更是一位伟大的工程师，王维评价他'巧思绝世'。国际天文学联合会将月球背面的一座环形山命名为'郭守敬山'。",
            "content": [
                {
                    "title": "一、四海测验与《授时历》：精密科学的巅峰",
                    "text": "<p>1276年，元军攻占临安，天下一统。忽必烈决定修订新历，任命郭守敬等人负责。郭守敬提出了'历之本在于测验，而测验之器莫先仪表'的思想。他在受命后，首先创制了高表、简仪等一系列新式仪器，然后在全国设立了27个观测点（<strong>四海测验</strong>），进行大规模的同步观测。这些观测点最北到西伯利亚（北海），最南到南海中的黄岩岛（南海），最东到朝鲜半岛，最西到滇池，范围之广前所未有。<br><br>基于数年积累的庞大实测数据，并采用极其精密的数学计算（如招差术，即三次内插法），1280年，《授时历》编成。该历法取'敬授民时'之意，定一回归年长度为<strong>365.2425日</strong>。这一数值与地球绕太阳公转的实际周期仅差26秒，与目前世界通用的格里高利历（公历）完全一致，但比欧洲早确立了300多年（格里高利历制定于1582年）。《授时历》颁行后，沿用了360多年，是中国历史上使用时间最长的历法。</p>"
                },
                {
                    "title": "二、巧思神工：天文仪器的革命性创新",
                    "text": "<p>为了提高观测精度，郭守敬大胆创新，废除了自汉唐以来结构复杂的浑仪，创制了<strong>简仪</strong>、高表、仰仪、景符等十多种新仪器。其中最著名的是简仪。他创造性地将浑仪中的赤道经纬仪和地平经纬仪分开，去除了不必要的圆环，避免了遮挡，使得观测视野更开阔，读数更精确。其设计原理和结构（如赤道装置、赤道环），与现代光学望远镜的机械结构有着惊人的相似之处，比丹麦天文学家第谷的发明早了300年。这些仪器展现了中国古代精密机械制造的高峰，原本陈列在大都司天台，后虽被毁，但部分复制品现存于南京紫金山天文台。</p>"
                },
                {
                    "title": "三、通惠河：大都的水脉与生命线",
                    "text": "<p>元大都作为帝国首都，人口百万，粮食主要靠南方漕运。为了解决最后一段'通州到大都'的运输瓶颈，郭守敬主持开凿了<strong>通惠河</strong>。这项工程难度极大，因为大都地势西高东低。他踏遍西山，寻找水源，最终引白浮泉水入城，汇入积水潭。为了解决地形高差问题，他设计了一系列<strong>船闸</strong>（斗门），即'柏闸'，通过控制闸门开合来调节水位，使粮船能够逐级'爬坡'进入大都。通惠河建成后，京杭大运河全线贯通，南方粮船可以直抵大都城内的积水潭（今什刹海），出现'舳舻蔽水'的繁荣景象。忽必烈大喜，亲笔题名'通惠河'。此外，他还主持了许多地区的水利灌溉工程，造福一方。</p>"
                }
            ],
            "exam_points": [
                {
                    "title": "天文学",
                    "desc": "编制《授时历》（365.2425天）；四海测验。"
                },
                {
                    "title": "仪器",
                    "desc": "发明简仪（简化浑仪）；高表。"
                },
                {
                    "title": "水利",
                    "desc": "主持开凿通惠河，解决大都漕运。"
                },
                {
                    "title": "地位",
                    "desc": "元朝科技高峰的代表；世界级科学家。"
                }
            ],
            "impact": {
                "reality": "极大地促进了农业生产（准确授时）和漕运经济（水利便利）。",
                "legacy": "代表了中国古代科技的巅峰；《授时历》传播到朝鲜、日本，影响深远；其科学精神（实测、创新）值得后世学习。"
            },
            "relations": [
                {
                    "text": "元朝",
                    "url": "detail_yuan.html"
                },
                {
                    "text": "忽必烈",
                    "url": "topic_kublai.html"
                }
            ],
            "graph": {
                "nodes": [
                    {
                        "id": "guo",
                        "label": "郭守敬",
                        "val": 30,
                        "group": "core",
                        "url": "topic_guoshoujing.html"
                    },
                    {
                        "id": "shoushi",
                        "label": "授时历",
                        "val": 25,
                        "group": "book",
                        "url": "topic_guoshoujing.html"
                    },
                    {
                        "id": "jianyi",
                        "label": "简仪",
                        "val": 25,
                        "group": "object",
                        "url": "topic_guoshoujing.html"
                    },
                    {
                        "id": "tonghui",
                        "label": "通惠河",
                        "val": 20,
                        "group": "place",
                        "url": "topic_guoshoujing.html"
                    }
                ],
                "edges": [
                    {
                        "source": "guo",
                        "target": "shoushi",
                        "label": "编制"
                    },
                    {
                        "source": "guo",
                        "target": "jianyi",
                        "label": "发明"
                    },
                    {
                        "source": "guo",
                        "target": "tonghui",
                        "label": "开凿"
                    }
                ]
            }
        },
        {
            "id": "topic_guanhanqing",
            "title": "梨园领袖：关汉卿与元曲 (Guan Hanqing and Yuan Drama)",
            "type": "china",
            "year": "元朝",
            "summary": "关汉卿（约1220-1300），由金入元，号已斋叟，大都人，元代最伟大的戏剧家，被称为'曲圣'，位列'元曲四大家'之首。他生活在元朝废除科举（或科举不兴）的时代，作为地位低下的文人，他混迹于勾栏瓦舍，熟悉底层人民的苦难。他一生创作了60多部杂剧，现存18部，代表作<strong>《窦娥冤》</strong>是中国悲剧文学的巅峰之作。他的作品语言通俗辛辣，充满了反抗精神，是元代市民文化的杰出代表。",
            "content": [
                {
                    "title": "一、愤怒出诗人：元曲的兴起背景",
                    "text": "<p>元朝初期，科举停废，汉族文人仕途无望，地位一落千丈（社会上流传'八娼九儒十丐'的说法，虽有夸张，反映了文人地位的边缘化）。大量的才子为了谋生，不得不放下身段，流落市井，将才情倾注于戏剧创作，与勾栏艺人合作。这种文人与市民文化的结合，催生了<strong>元杂剧</strong>的繁荣。元曲（包括杂剧和散曲）成为了继唐诗、宋词之后的又一文学高峰。它使用白话，通俗易懂，题材广泛，深受市民阶层欢迎。大都成为了元杂剧的中心，关汉卿正是在这样的环境中脱颖而出。</p>"
                },
                {
                    "title": "二、感天动地窦娥冤：现实批判与悲剧美学",
                    "text": "<p>《窦娥冤》是关汉卿的扛鼎之作，也是中国十大悲剧之首。剧中描写了年轻寡妇窦娥，被无赖张驴儿诬陷杀人，又被贪官桃杌（代表黑暗的统治者）屈打成招，被判斩刑。临刑前，窦娥发下三桩誓愿：血溅白练、六月飞雪、大旱三年。结果三桩誓愿一一应验，连老天都被感动。这部戏通过神话色彩，控诉了元代社会的极度黑暗和司法的不公（'地也，你不分好歹何为地？天也，你错勘贤愚枉做天！'），表达了人民对正义的强烈渴望和对压迫的愤怒。窦娥的形象，既有传统妇女的善良，又有敢于反抗的刚烈，具有极高的审美价值。</p>"
                },
                {
                    "title": "三、铜豌豆精神：浪子的风骨",
                    "text": "<p>关汉卿是个性格豪爽、风流倜傥的浪子。他在散曲《不伏老》中自画像：'我是个蒸不烂、煮不熟、捶不扁、炒不爆、响当当一粒<strong>铜豌豆</strong>。' 他精通骑马、踢球、狩猎、下棋、歌舞，是个全能的玩家。但在这种玩世不恭的外表下，是一颗傲视权贵、绝不向命运屈服的顽强灵魂。他同情妓女等底层女性（如《救风尘》中的赵盼儿，《望江亭》中的谭记儿），批判虚伪的礼教。他的创作风格涵盖了公案、爱情、历史等多种题材，对后世的戏曲（如昆曲、京剧）产生了巨大的奠基作用，王国维称其'一空依傍，自铸伟词'。</p>"
                }
            ],
            "exam_points": [
                {
                    "title": "地位",
                    "desc": "元曲四大家之首（关漢卿、马致远、白朴、郑光祖）；'曲圣'。"
                },
                {
                    "title": "代表作",
                    "desc": "《窦娥冤》（感天动地）；《救风尘》；《单刀会》。"
                },
                {
                    "title": "精神",
                    "desc": "铜豌豆精神（顽强反抗）；现实主义批判。"
                }
            ],
            "impact": {
                "reality": "丰富了市民的文化生活，成为了宣泄社会不满的窗口。",
                "legacy": "奠定了中国古典戏曲的基础；关汉卿被评为'世界文化名人'；《窦娥冤》流传八百年不衰。"
            },
            "relations": [
                {
                    "text": "元朝",
                    "url": "detail_yuan.html"
                },
                {
                    "text": "商业革命",
                    "url": "topic_commerce.html"
                }
            ],
            "graph": {
                "nodes": [
                    {
                        "id": "guan",
                        "label": "关汉卿",
                        "val": 30,
                        "group": "core",
                        "url": "topic_guanhanqing.html"
                    },
                    {
                        "id": "doue",
                        "label": "窦娥冤",
                        "val": 25,
                        "group": "book",
                        "url": "topic_guanhanqing.html"
                    },
                    {
                        "id": "zaju",
                        "label": "元杂剧",
                        "val": 25,
                        "group": "style",
                        "url": "topic_guanhanqing.html"
                    },
                    {
                        "id": "tongwandou",
                        "label": "铜豌豆",
                        "val": 20,
                        "group": "concept",
                        "url": "topic_guanhanqing.html"
                    }
                ],
                "edges": [
                    {
                        "source": "guan",
                        "target": "doue",
                        "label": "创作"
                    },
                    {
                        "source": "guan",
                        "target": "zaju",
                        "label": "代表"
                    },
                    {
                        "source": "guan",
                        "target": "tongwandou",
                        "label": "自喻"
                    }
                ]
            }
        },
        {
            "id": "topic_marcopolo",
            "title": "东方见闻录：马可·波罗 (Marco Polo)",
            "type": "world",
            "year": "1275年-1291年",
            "summary": "马可·波罗（1254-1324），威尼斯旅行家。1271年，他随父亲和叔叔沿丝绸之路东行，历经四年到达元朝上都。他受到元世祖忽必烈的赏识，在元朝为官17年，游历了中国各地（大都、杭州、云南等）。回国后，他在热那亚监狱中口述，由鲁斯蒂谦笔录了<strong>《马可·波罗行纪》</strong>。书中对东方富庶（'黄金遍地'）的夸张描写，震惊了欧洲，点燃了欧洲人对东方的向往，直接推动了后来的新航路开辟。",
            "content": [
                {
                    "title": "一、漫漫东行路：穿越丝路",
                    "text": "<p>13世纪，随着蒙古帝国的建立，从欧洲到中国的陆路交通变得畅通无阻（'蒙古治世'）。1271年，17岁的马可·波罗随父亲尼古拉、叔叔玛费欧从威尼斯出发，带着教皇的信件前往神秘的东方。他们穿过地中海，经过叙利亚、波斯，翻越帕米尔高原，穿越塔克拉玛干沙漠（流沙），历尽艰辛，于1275年抵达元上都（内蒙古正蓝旗）。这一壮举展示了人类探索未知的勇气。</p>"
                },
                {
                    "title": "二、在元朝的日子：侍奉大汗",
                    "text": "<p>忽必烈非常喜欢这个聪明的欧洲年轻人，让他担任侍从，并派往各地执行任务（甚至可能担任过扬州的地方官，虽有争议）。马可·波罗在华居住长达17年，亲眼目睹了元朝的繁荣。在书中，他详细描述了大都规划整齐的街道、皇宫的奢华、<strong>纸币</strong>的流通、<strong>煤炭</strong>（'黑色的石头'）的使用以及高效的驿站系统。他特别赞叹南宋故都<strong>杭州</strong>（行在）是'世界上最美丽华贵之天城'，并详细记录了那里的成千上万座桥梁、繁华的市场和市民的生活。</p>"
                },
                {
                    "title": "三、世界第一奇书：新航路的召唤",
                    "text": "<p>1291年，马可·波罗奉命护送阔阔真公主远嫁波斯，随后返回威尼斯。后来在一次与热那亚的海战中被俘，在狱中口述了他在东方的见闻，由狱友鲁斯蒂谦笔录成书。<strong>《马可·波罗行纪》</strong>（又名《东方见闻录》）向封闭的贫穷的欧洲展示了一个远比欧洲富庶、文明、强大的东方世界。书中提到日本'黄金铺地'，中国遍地绫罗绸缎、香料珠宝。虽然当时很多人不信，称他为'百万先生'（吹牛），但这本书唤醒了欧洲的扩张欲望。两百年后，哥伦布当年出海时，随身携带的正是这本书，他坚信一直向西航行就能到达马可·波罗笔下的东方。</p>"
                }
            ],
            "exam_points": [
                {
                    "title": "事迹",
                    "desc": "1275年到达元朝；受忽必烈赏识；在华17年。"
                },
                {
                    "title": "著作",
                    "desc": "《马可·波罗行纪》（《东方见闻录》）。"
                },
                {
                    "title": "描述",
                    "desc": "赞叹杭州为'天城'；记载纸币、煤炭。"
                },
                {
                    "title": "影响",
                    "desc": "激起了欧洲人对东方的向往，成为新航路开辟的诱因之一。"
                }
            ],
            "impact": {
                "reality": "促进了中西文化的直接交流，记录了元朝的繁华。",
                "legacy": "改变了世界历史进程（地理大发现）；是中西友好的象征。"
            },
            "relations": [
                {
                    "text": "元朝",
                    "url": "detail_yuan.html"
                },
                {
                    "text": "忽必烈",
                    "url": "topic_kublai.html"
                }
            ],
            "graph": {
                "nodes": [
                    {
                        "id": "marco",
                        "label": "马可·波罗",
                        "val": 30,
                        "group": "core",
                        "url": "topic_marcopolo.html"
                    },
                    {
                        "id": "book",
                        "label": "东方见闻录",
                        "val": 25,
                        "group": "book",
                        "url": "topic_marcopolo.html"
                    },
                    {
                        "id": "kublai",
                        "label": "忽必烈",
                        "val": 20,
                        "group": "emperor",
                        "url": "topic_kublai.html"
                    },
                    {
                        "id": "hangzhou",
                        "label": "杭州",
                        "val": 20,
                        "group": "place",
                        "url": "topic_marcopolo.html"
                    }
                ],
                "edges": [
                    {
                        "source": "marco",
                        "target": "book",
                        "label": "口述"
                    },
                    {
                        "source": "kublai",
                        "target": "marco",
                        "label": "接见"
                    },
                    {
                        "source": "marco",
                        "target": "hangzhou",
                        "label": "赞叹"
                    }
                ]
            }
        },
        {
            "id": "topic_yuan_society",
            "title": "等级与融合：四等人制 (Four Class System)",
            "type": "china",
            "year": "元朝",
            "summary": "元朝为了维护蒙古贵族的特权统治性，采取了民族分化政策，将全国人民分为四个等级：<strong>蒙古人、色目人、汉人、南人</strong>。这就是著名的'四等人制'（虽未见于正式法典，但实际上存在）。这四个等级在任官、科举、刑律等各方面待遇迥异。这种民族歧视政策激化了社会矛盾，加速了元朝的灭亡。但与此同时，元朝空前的大一统局面也促进了各民族的长期杂居和融合，波斯、阿拉伯人与汉、蒙、畏兀儿等族融合，形成了一个新的民族——<strong>回族</strong>。",
            "content": [
                {
                    "title": "一、不平等的金字塔：四等人",
                    "text": "<p><strong>1. 蒙古人：</strong> 处于统治地位，享有各种特权，担任中央和地方的主要官职（达鲁花赤）。<br><strong>2. 色目人：</strong> 意为'各色名目之人'，主要指西域人（如波斯、阿拉伯、畏兀儿人）。他们善于理财和经商，被元朝统治者视为助手，地位仅次于蒙古人。<br><strong>3. 汉人：</strong> 原金朝统治区的汉人、女真人和契丹人。<br><strong>4. 南人：</strong> 原南宋统治区的汉人，人数最多，但地位最低（因为南宋抵抗最久，被认为最不可靠）。<br><br>不平等体现在方方面面：在科举中，蒙古、色目人考两场，题目容易；汉人、南人考三场，题目难，且录取名额相同（意味着汉南人竞争极惨烈）。在法律上，蒙古人打死汉人只需罚交烧埋银，而汉人打死蒙古人则要偿命。汉人甚至被禁止拥有兵器、养马。</p>"
                },
                {
                    "title": "二、大杂居小聚居：回族的形成",
                    "text": "<p>尽管政策上存在歧视，但民间的民族融合却从未停止。随着蒙古西征和元朝的建立，大量的波斯人、阿拉伯人、中亚人迁入中国，他们被称为'回回'。这些人在中国定居后，与汉、蒙、畏兀儿等民族长期杂居，通婚，在经济文化上相互影响。他们保留了伊斯兰教（清真）信仰和生活习惯，但逐渐改说汉语。经过元朝一百年的融合，形成了一个新的民族共同体——<strong>回族</strong>。此外，契丹、女真等民族在元朝也逐渐融入汉族，元朝成为了各民族大融合的熔炉。</p>"
                },
                {
                    "title": "三、矛盾与崩溃：驱逐胡虏",
                    "text": "<p>四等人制人为地制造了民族隔阂和阶级对立。元朝中后期，丞相伯颜甚至一度提议要杀光'张、王、刘、李、赵'五姓汉人。这种极端的压迫最终引发了猛烈的反抗。1351年，韩山童、刘福通发动红巾军起义时，口号之一就是'驱逐胡虏，恢复中华'。朱元璋建立明朝后，发布的《谕中原檄》，也强调恢复汉家衣冠。四等人制成为了元朝短命（不到百年）的重要推手，也给后世留下了深刻的教训：民族平等是国家稳定的基石。</p>"
                }
            ],
            "exam_points": [
                {
                    "title": "四等人",
                    "desc": "蒙古人（第一等）；色目人（第二等）；汉人（北方，第三等）；南人（南方，第四等）。"
                },
                {
                    "title": "回族形成",
                    "desc": "波斯、阿拉伯人与汉蒙融合，形成新民族（信仰伊斯兰教）。"
                },
                {
                    "title": "评价",
                    "desc": "民族歧视政策加速了元朝灭亡；但客观上促进了民族融合。"
                }
            ],
            "impact": {
                "reality": "导致了元朝统治基础薄弱，享国不足百年（98年）。",
                "legacy": "回族的形成丰富了中华民族的多元一体；教训：民族平等是国家稳定的基石。"
            },
            "relations": [
                {
                    "text": "元朝",
                    "url": "detail_yuan.html"
                },
                {
                    "text": "行省制",
                    "url": "topic_xingsheng.html"
                }
            ],
            "graph": {
                "nodes": [
                    {
                        "id": "fourclass",
                        "label": "四等人制",
                        "val": 30,
                        "group": "core",
                        "url": "topic_yuan_society.html"
                    },
                    {
                        "id": "mongol",
                        "label": "蒙古人",
                        "val": 25,
                        "group": "people",
                        "url": "topic_yuan_society.html"
                    },
                    {
                        "id": "semu",
                        "label": "色目人",
                        "val": 25,
                        "group": "people",
                        "url": "topic_yuan_society.html"
                    },
                    {
                        "id": "hui",
                        "label": "回族",
                        "val": 25,
                        "group": "people",
                        "url": "topic_yuan_society.html"
                    }
                ],
                "edges": [
                    {
                        "source": "fourclass",
                        "target": "mongol",
                        "label": "第一等"
                    },
                    {
                        "source": "fourclass",
                        "target": "semu",
                        "label": "第二等"
                    },
                    {
                        "source": "fourclass",
                        "target": "hui",
                        "label": "形成"
                    }
                ]
            }
        }
    ]
}